llm_logger/__init__.py
llm_logger/cli.py
llm_logger/config.py
llm_logger/log_viewer.py
llm_logger/logger.py
llm_logger/static/common.js
llm_logger/static/index.html
llm_logger/static/index.js
llm_logger/static/session.html
llm_logger/static/style.css
llm_logger/static/viewer.js
llm_logger/wrappers/__init__.py
llm_logger/wrappers/anthropic_wrapper.py
llm_logger/wrappers/openai_wrapper.py
llm_logger-0.5.4.dist-info/licenses/LICENSE
llm_logger-0.5.4.dist-info/METADATA
llm_logger-0.5.4.dist-info/WHEEL
llm_logger-0.5.4.dist-info/entry_points.txt
llm_logger-0.5.4.dist-info/top_level.txt
llm_logger-0.5.4.dist-info/RECORD
