Metadata-Version: 2.4
Name: llm_logger
Version: 0.5.4
Summary: Lightweight LLM call logger for OpenAI/Anthropic
Author-email: Avtar Khalsa <akhalsa43@gmail.com>
License: MIT
Project-URL: Homepage, https://github.com/akhalsa/llm_debugger
Requires-Python: >=3.8
License-File: LICENSE
Requires-Dist: openai>=1.0
Requires-Dist: fastapi
Requires-Dist: uvicorn
Dynamic: license-file
